{"config":{"output_file":null,"full_docs":false,"pub_only":true,"reachable_only":true,"distro_crate":false,"signatures":false,"borrow_data":false},"version":"0.19.1","compilation":{"directory":"/Users/doviethoang/.cargo/registry/src/github.com-1ecc6299db9ec823/clru-0.2.1","program":"/Users/doviethoang/.rustup/toolchains/stable-x86_64-apple-darwin/bin/rls","arguments":["--crate-name","clru","--edition=2018","/Users/doviethoang/.cargo/registry/src/github.com-1ecc6299db9ec823/clru-0.2.1/src/lib.rs","--json=diagnostic-rendered-ansi,artifacts,future-incompat","--crate-type","lib","--emit=dep-info,metadata","-C","embed-bitcode=no","-C","split-debuginfo=unpacked","-C","debuginfo=2","-C","metadata=2b921db4ff06aa28","-C","extra-filename=-2b921db4ff06aa28","--out-dir","/Users/doviethoang/Desktop/github/cw-contracts/contracts/voting/target/rls/debug/deps","-L","dependency=/Users/doviethoang/Desktop/github/cw-contracts/contracts/voting/target/rls/debug/deps","--cap-lints","allow","--error-format=json","--sysroot","/Users/doviethoang/.rustup/toolchains/stable-x86_64-apple-darwin"],"output":"/Users/doviethoang/Desktop/github/cw-contracts/contracts/voting/target/rls/debug/deps/libclru-2b921db4ff06aa28.rmeta"},"prelude":{"crate_id":{"name":"clru","disambiguator":[17757335696238058643,0]},"crate_root":"/Users/doviethoang/.cargo/registry/src/github.com-1ecc6299db9ec823/clru-0.2.1/src","external_crates":[{"file_name":"/Users/doviethoang/.cargo/registry/src/github.com-1ecc6299db9ec823/clru-0.2.1/src/lib.rs","num":1,"id":{"name":"std","disambiguator":[8736441298905945133,0]}},{"file_name":"/Users/doviethoang/.cargo/registry/src/github.com-1ecc6299db9ec823/clru-0.2.1/src/lib.rs","num":2,"id":{"name":"core","disambiguator":[14793976659495462539,0]}},{"file_name":"/Users/doviethoang/.cargo/registry/src/github.com-1ecc6299db9ec823/clru-0.2.1/src/lib.rs","num":3,"id":{"name":"compiler_builtins","disambiguator":[3402831840469434398,0]}},{"file_name":"/Users/doviethoang/.cargo/registry/src/github.com-1ecc6299db9ec823/clru-0.2.1/src/lib.rs","num":4,"id":{"name":"rustc_std_workspace_core","disambiguator":[10266006331935790141,0]}},{"file_name":"/Users/doviethoang/.cargo/registry/src/github.com-1ecc6299db9ec823/clru-0.2.1/src/lib.rs","num":5,"id":{"name":"alloc","disambiguator":[3256146445313423250,0]}},{"file_name":"/Users/doviethoang/.cargo/registry/src/github.com-1ecc6299db9ec823/clru-0.2.1/src/lib.rs","num":6,"id":{"name":"libc","disambiguator":[17904618012795691138,0]}},{"file_name":"/Users/doviethoang/.cargo/registry/src/github.com-1ecc6299db9ec823/clru-0.2.1/src/lib.rs","num":7,"id":{"name":"unwind","disambiguator":[9322387616446168443,0]}},{"file_name":"/Users/doviethoang/.cargo/registry/src/github.com-1ecc6299db9ec823/clru-0.2.1/src/lib.rs","num":8,"id":{"name":"cfg_if","disambiguator":[3101585505833515335,0]}},{"file_name":"/Users/doviethoang/.cargo/registry/src/github.com-1ecc6299db9ec823/clru-0.2.1/src/lib.rs","num":9,"id":{"name":"hashbrown","disambiguator":[9998121223216013160,0]}},{"file_name":"/Users/doviethoang/.cargo/registry/src/github.com-1ecc6299db9ec823/clru-0.2.1/src/lib.rs","num":10,"id":{"name":"rustc_std_workspace_alloc","disambiguator":[13604153592636442655,0]}},{"file_name":"/Users/doviethoang/.cargo/registry/src/github.com-1ecc6299db9ec823/clru-0.2.1/src/lib.rs","num":11,"id":{"name":"std_detect","disambiguator":[4682215639508348019,0]}},{"file_name":"/Users/doviethoang/.cargo/registry/src/github.com-1ecc6299db9ec823/clru-0.2.1/src/lib.rs","num":12,"id":{"name":"rustc_demangle","disambiguator":[681692869457277629,0]}},{"file_name":"/Users/doviethoang/.cargo/registry/src/github.com-1ecc6299db9ec823/clru-0.2.1/src/lib.rs","num":13,"id":{"name":"addr2line","disambiguator":[14282542057858629160,0]}},{"file_name":"/Users/doviethoang/.cargo/registry/src/github.com-1ecc6299db9ec823/clru-0.2.1/src/lib.rs","num":14,"id":{"name":"gimli","disambiguator":[14550073586256240635,0]}},{"file_name":"/Users/doviethoang/.cargo/registry/src/github.com-1ecc6299db9ec823/clru-0.2.1/src/lib.rs","num":15,"id":{"name":"object","disambiguator":[6281633846692226065,0]}},{"file_name":"/Users/doviethoang/.cargo/registry/src/github.com-1ecc6299db9ec823/clru-0.2.1/src/lib.rs","num":16,"id":{"name":"memchr","disambiguator":[17361906875064838028,0]}},{"file_name":"/Users/doviethoang/.cargo/registry/src/github.com-1ecc6299db9ec823/clru-0.2.1/src/lib.rs","num":17,"id":{"name":"panic_unwind","disambiguator":[16875744454975590306,0]}}],"span":{"file_name":"/Users/doviethoang/.cargo/registry/src/github.com-1ecc6299db9ec823/clru-0.2.1/src/lib.rs","byte_start":0,"byte_end":41632,"line_start":1,"line_end":1387,"column_start":1,"column_end":2}},"imports":[],"defs":[{"kind":"Mod","id":{"krate":0,"index":0},"span":{"file_name":"/Users/doviethoang/.cargo/registry/src/github.com-1ecc6299db9ec823/clru-0.2.1/src/lib.rs","byte_start":0,"byte_end":41632,"line_start":1,"line_end":1387,"column_start":1,"column_end":2},"name":"","qualname":"::","value":"/Users/doviethoang/.cargo/registry/src/github.com-1ecc6299db9ec823/clru-0.2.1/src/lib.rs","parent":null,"children":[{"krate":0,"index":1},{"krate":0,"index":2},{"krate":0,"index":3},{"krate":0,"index":6},{"krate":0,"index":9},{"krate":0,"index":12},{"krate":0,"index":15},{"krate":0,"index":18},{"krate":0,"index":19},{"krate":0,"index":22},{"krate":0,"index":23},{"krate":0,"index":25},{"krate":0,"index":196},{"krate":0,"index":201},{"krate":0,"index":204},{"krate":0,"index":210},{"krate":0,"index":28},{"krate":0,"index":213},{"krate":0,"index":220},{"krate":0,"index":224},{"krate":0,"index":58},{"krate":0,"index":64},{"krate":0,"index":68},{"krate":0,"index":72},{"krate":0,"index":79},{"krate":0,"index":85},{"krate":0,"index":89},{"krate":0,"index":228},{"krate":0,"index":232},{"krate":0,"index":235},{"krate":0,"index":238},{"krate":0,"index":240},{"krate":0,"index":243},{"krate":0,"index":247},{"krate":0,"index":249},{"krate":0,"index":253},{"krate":0,"index":257},{"krate":0,"index":260},{"krate":0,"index":263},{"krate":0,"index":265},{"krate":0,"index":268},{"krate":0,"index":272},{"krate":0,"index":274},{"krate":0,"index":93},{"krate":0,"index":96},{"krate":0,"index":100},{"krate":0,"index":106},{"krate":0,"index":110},{"krate":0,"index":278},{"krate":0,"index":283},{"krate":0,"index":288},{"krate":0,"index":153},{"krate":0,"index":161},{"krate":0,"index":167},{"krate":0,"index":172},{"krate":0,"index":177},{"krate":0,"index":185},{"krate":0,"index":191}],"decl_id":null,"docs":" Another LRU cache implementation in rust.\n The cache is backed by a [HashMap](https://doc.rust-lang.org/std/collections/struct.HashMap.html) and thus\n offers a O(1) time complexity for common operations:\n * `get` / `get_mut`\n * `put` / `pop`\n * `peek` / `peek_mut`","sig":null,"attributes":[{"value":"/ Another LRU cache implementation in rust.","span":{"file_name":"/Users/doviethoang/.cargo/registry/src/github.com-1ecc6299db9ec823/clru-0.2.1/src/lib.rs","byte_start":0,"byte_end":45,"line_start":1,"line_end":1,"column_start":1,"column_end":46}},{"value":"/ The cache is backed by a [HashMap](https://doc.rust-lang.org/std/collections/struct.HashMap.html) and thus","span":{"file_name":"/Users/doviethoang/.cargo/registry/src/github.com-1ecc6299db9ec823/clru-0.2.1/src/lib.rs","byte_start":46,"byte_end":156,"line_start":2,"line_end":2,"column_start":1,"column_end":111}},{"value":"/ offers a O(1) time complexity for common operations:","span":{"file_name":"/Users/doviethoang/.cargo/registry/src/github.com-1ecc6299db9ec823/clru-0.2.1/src/lib.rs","byte_start":157,"byte_end":213,"line_start":3,"line_end":3,"column_start":1,"column_end":57}},{"value":"/ * `get` / `get_mut`","span":{"file_name":"/Users/doviethoang/.cargo/registry/src/github.com-1ecc6299db9ec823/clru-0.2.1/src/lib.rs","byte_start":214,"byte_end":237,"line_start":4,"line_end":4,"column_start":1,"column_end":24}},{"value":"/ * `put` / `pop`","span":{"file_name":"/Users/doviethoang/.cargo/registry/src/github.com-1ecc6299db9ec823/clru-0.2.1/src/lib.rs","byte_start":238,"byte_end":257,"line_start":5,"line_end":5,"column_start":1,"column_end":20}},{"value":"/ * `peek` / `peek_mut`","span":{"file_name":"/Users/doviethoang/.cargo/registry/src/github.com-1ecc6299db9ec823/clru-0.2.1/src/lib.rs","byte_start":258,"byte_end":283,"line_start":6,"line_end":6,"column_start":1,"column_end":26}},{"value":"/","span":{"file_name":"/Users/doviethoang/.cargo/registry/src/github.com-1ecc6299db9ec823/clru-0.2.1/src/lib.rs","byte_start":284,"byte_end":287,"line_start":7,"line_end":7,"column_start":1,"column_end":4}},{"value":"/ ## Example","span":{"file_name":"/Users/doviethoang/.cargo/registry/src/github.com-1ecc6299db9ec823/clru-0.2.1/src/lib.rs","byte_start":288,"byte_end":302,"line_start":8,"line_end":8,"column_start":1,"column_end":15}},{"value":"/","span":{"file_name":"/Users/doviethoang/.cargo/registry/src/github.com-1ecc6299db9ec823/clru-0.2.1/src/lib.rs","byte_start":303,"byte_end":306,"line_start":9,"line_end":9,"column_start":1,"column_end":4}},{"value":"/ ```rust","span":{"file_name":"/Users/doviethoang/.cargo/registry/src/github.com-1ecc6299db9ec823/clru-0.2.1/src/lib.rs","byte_start":307,"byte_end":318,"line_start":10,"line_end":10,"column_start":1,"column_end":12}},{"value":"/","span":{"file_name":"/Users/doviethoang/.cargo/registry/src/github.com-1ecc6299db9ec823/clru-0.2.1/src/lib.rs","byte_start":319,"byte_end":322,"line_start":11,"line_end":11,"column_start":1,"column_end":4}},{"value":"/ use clru::CLruCache;","span":{"file_name":"/Users/doviethoang/.cargo/registry/src/github.com-1ecc6299db9ec823/clru-0.2.1/src/lib.rs","byte_start":323,"byte_end":347,"line_start":12,"line_end":12,"column_start":1,"column_end":25}},{"value":"/","span":{"file_name":"/Users/doviethoang/.cargo/registry/src/github.com-1ecc6299db9ec823/clru-0.2.1/src/lib.rs","byte_start":348,"byte_end":351,"line_start":13,"line_end":13,"column_start":1,"column_end":4}},{"value":"/ let mut cache = CLruCache::new(2);","span":{"file_name":"/Users/doviethoang/.cargo/registry/src/github.com-1ecc6299db9ec823/clru-0.2.1/src/lib.rs","byte_start":352,"byte_end":390,"line_start":14,"line_end":14,"column_start":1,"column_end":39}},{"value":"/ cache.put(\"apple\".to_string(), 3);","span":{"file_name":"/Users/doviethoang/.cargo/registry/src/github.com-1ecc6299db9ec823/clru-0.2.1/src/lib.rs","byte_start":391,"byte_end":429,"line_start":15,"line_end":15,"column_start":1,"column_end":39}},{"value":"/ cache.put(\"banana\".to_string(), 2);","span":{"file_name":"/Users/doviethoang/.cargo/registry/src/github.com-1ecc6299db9ec823/clru-0.2.1/src/lib.rs","byte_start":430,"byte_end":469,"line_start":16,"line_end":16,"column_start":1,"column_end":40}},{"value":"/","span":{"file_name":"/Users/doviethoang/.cargo/registry/src/github.com-1ecc6299db9ec823/clru-0.2.1/src/lib.rs","byte_start":470,"byte_end":473,"line_start":17,"line_end":17,"column_start":1,"column_end":4}},{"value":"/ assert_eq!(cache.get(\"apple\"), Some(&3));","span":{"file_name":"/Users/doviethoang/.cargo/registry/src/github.com-1ecc6299db9ec823/clru-0.2.1/src/lib.rs","byte_start":474,"byte_end":519,"line_start":18,"line_end":18,"column_start":1,"column_end":46}},{"value":"/ assert_eq!(cache.get(\"banana\"), Some(&2));","span":{"file_name":"/Users/doviethoang/.cargo/registry/src/github.com-1ecc6299db9ec823/clru-0.2.1/src/lib.rs","byte_start":520,"byte_end":566,"line_start":19,"line_end":19,"column_start":1,"column_end":47}},{"value":"/ assert!(cache.get(\"pear\").is_none());","span":{"file_name":"/Users/doviethoang/.cargo/registry/src/github.com-1ecc6299db9ec823/clru-0.2.1/src/lib.rs","byte_start":567,"byte_end":608,"line_start":20,"line_end":20,"column_start":1,"column_end":42}},{"value":"/","span":{"file_name":"/Users/doviethoang/.cargo/registry/src/github.com-1ecc6299db9ec823/clru-0.2.1/src/lib.rs","byte_start":609,"byte_end":612,"line_start":21,"line_end":21,"column_start":1,"column_end":4}},{"value":"/ assert_eq!(cache.put(\"banana\".to_string(), 4), Some(2));","span":{"file_name":"/Users/doviethoang/.cargo/registry/src/github.com-1ecc6299db9ec823/clru-0.2.1/src/lib.rs","byte_start":613,"byte_end":673,"line_start":22,"line_end":22,"column_start":1,"column_end":61}},{"value":"/ assert_eq!(cache.put(\"pear\".to_string(), 5), None);","span":{"file_name":"/Users/doviethoang/.cargo/registry/src/github.com-1ecc6299db9ec823/clru-0.2.1/src/lib.rs","byte_start":674,"byte_end":729,"line_start":23,"line_end":23,"column_start":1,"column_end":56}},{"value":"/","span":{"file_name":"/Users/doviethoang/.cargo/registry/src/github.com-1ecc6299db9ec823/clru-0.2.1/src/lib.rs","byte_start":730,"byte_end":733,"line_start":24,"line_end":24,"column_start":1,"column_end":4}},{"value":"/ assert_eq!(cache.get(\"pear\"), Some(&5));","span":{"file_name":"/Users/doviethoang/.cargo/registry/src/github.com-1ecc6299db9ec823/clru-0.2.1/src/lib.rs","byte_start":734,"byte_end":778,"line_start":25,"line_end":25,"column_start":1,"column_end":45}},{"value":"/ assert_eq!(cache.get(\"banana\"), Some(&4));","span":{"file_name":"/Users/doviethoang/.cargo/registry/src/github.com-1ecc6299db9ec823/clru-0.2.1/src/lib.rs","byte_start":779,"byte_end":825,"line_start":26,"line_end":26,"column_start":1,"column_end":47}},{"value":"/ assert!(cache.get(\"apple\").is_none());","span":{"file_name":"/Users/doviethoang/.cargo/registry/src/github.com-1ecc6299db9ec823/clru-0.2.1/src/lib.rs","byte_start":826,"byte_end":868,"line_start":27,"line_end":27,"column_start":1,"column_end":43}},{"value":"/","span":{"file_name":"/Users/doviethoang/.cargo/registry/src/github.com-1ecc6299db9ec823/clru-0.2.1/src/lib.rs","byte_start":869,"byte_end":872,"line_start":28,"line_end":28,"column_start":1,"column_end":4}},{"value":"/ {","span":{"file_name":"/Users/doviethoang/.cargo/registry/src/github.com-1ecc6299db9ec823/clru-0.2.1/src/lib.rs","byte_start":873,"byte_end":878,"line_start":29,"line_end":29,"column_start":1,"column_end":6}},{"value":"/     let v = cache.get_mut(\"banana\").unwrap();","span":{"file_name":"/Users/doviethoang/.cargo/registry/src/github.com-1ecc6299db9ec823/clru-0.2.1/src/lib.rs","byte_start":879,"byte_end":928,"line_start":30,"line_end":30,"column_start":1,"column_end":50}},{"value":"/     *v = 6;","span":{"file_name":"/Users/doviethoang/.cargo/registry/src/github.com-1ecc6299db9ec823/clru-0.2.1/src/lib.rs","byte_start":929,"byte_end":944,"line_start":31,"line_end":31,"column_start":1,"column_end":16}},{"value":"/ }","span":{"file_name":"/Users/doviethoang/.cargo/registry/src/github.com-1ecc6299db9ec823/clru-0.2.1/src/lib.rs","byte_start":945,"byte_end":950,"line_start":32,"line_end":32,"column_start":1,"column_end":6}},{"value":"/","span":{"file_name":"/Users/doviethoang/.cargo/registry/src/github.com-1ecc6299db9ec823/clru-0.2.1/src/lib.rs","byte_start":951,"byte_end":954,"line_start":33,"line_end":33,"column_start":1,"column_end":4}},{"value":"/ assert_eq!(cache.get(\"banana\"), Some(&6));","span":{"file_name":"/Users/doviethoang/.cargo/registry/src/github.com-1ecc6299db9ec823/clru-0.2.1/src/lib.rs","byte_start":955,"byte_end":1001,"line_start":34,"line_end":34,"column_start":1,"column_end":47}},{"value":"/ ```","span":{"file_name":"/Users/doviethoang/.cargo/registry/src/github.com-1ecc6299db9ec823/clru-0.2.1/src/lib.rs","byte_start":1002,"byte_end":1009,"line_start":35,"line_end":35,"column_start":1,"column_end":8}},{"value":"deny(missing_docs)","span":{"file_name":"/Users/doviethoang/.cargo/registry/src/github.com-1ecc6299db9ec823/clru-0.2.1/src/lib.rs","byte_start":1011,"byte_end":1033,"line_start":37,"line_end":37,"column_start":1,"column_end":23}},{"value":"deny(unsafe_code)","span":{"file_name":"/Users/doviethoang/.cargo/registry/src/github.com-1ecc6299db9ec823/clru-0.2.1/src/lib.rs","byte_start":1034,"byte_end":1055,"line_start":38,"line_end":38,"column_start":1,"column_end":22}},{"value":"deny(warnings)","span":{"file_name":"/Users/doviethoang/.cargo/registry/src/github.com-1ecc6299db9ec823/clru-0.2.1/src/lib.rs","byte_start":1056,"byte_end":1074,"line_start":39,"line_end":39,"column_start":1,"column_end":19}}]},{"kind":"Struct","id":{"krate":0,"index":100},"span":{"file_name":"/Users/doviethoang/.cargo/registry/src/github.com-1ecc6299db9ec823/clru-0.2.1/src/lib.rs","byte_start":11956,"byte_end":11965,"line_start":409,"line_end":409,"column_start":12,"column_end":21},"name":"CLruCache","qualname":"::CLruCache","value":"CLruCache {  }","parent":null,"children":[{"krate":0,"index":104},{"krate":0,"index":105}],"decl_id":null,"docs":" An LRU cache with constant time operations.\n","sig":null,"attributes":[{"value":"/ An LRU cache with constant time operations.","span":{"file_name":"/Users/doviethoang/.cargo/registry/src/github.com-1ecc6299db9ec823/clru-0.2.1/src/lib.rs","byte_start":11897,"byte_end":11944,"line_start":408,"line_end":408,"column_start":1,"column_end":48}}]},{"kind":"Method","id":{"krate":0,"index":109},"span":{"file_name":"/Users/doviethoang/.cargo/registry/src/github.com-1ecc6299db9ec823/clru-0.2.1/src/lib.rs","byte_start":12194,"byte_end":12197,"line_start":416,"line_end":416,"column_start":12,"column_end":15},"name":"new","qualname":"<CLruCache<K, V>>::new","value":"pub fn new(usize) -> Self","parent":null,"children":[],"decl_id":null,"docs":" Creates a new LRU Cache that holds at most `capacity` items.\n","sig":null,"attributes":[{"value":"/ Creates a new LRU Cache that holds at most `capacity` items.","span":{"file_name":"/Users/doviethoang/.cargo/registry/src/github.com-1ecc6299db9ec823/clru-0.2.1/src/lib.rs","byte_start":12118,"byte_end":12182,"line_start":415,"line_end":415,"column_start":5,"column_end":69}}]},{"kind":"Method","id":{"krate":0,"index":114},"span":{"file_name":"/Users/doviethoang/.cargo/registry/src/github.com-1ecc6299db9ec823/clru-0.2.1/src/lib.rs","byte_start":12551,"byte_end":12562,"line_start":426,"line_end":426,"column_start":12,"column_end":23},"name":"with_hasher","qualname":"<CLruCache<K, V, S>>::with_hasher","value":"pub fn with_hasher(usize, S) -> Self","parent":null,"children":[],"decl_id":null,"docs":" Creates a new LRU Cache that holds at most `capacity` items and uses the provided hash builder to hash keys.\n","sig":null,"attributes":[{"value":"/ Creates a new LRU Cache that holds at most `capacity` items and uses the provided hash builder to hash keys.","span":{"file_name":"/Users/doviethoang/.cargo/registry/src/github.com-1ecc6299db9ec823/clru-0.2.1/src/lib.rs","byte_start":12427,"byte_end":12539,"line_start":425,"line_end":425,"column_start":5,"column_end":117}}]},{"kind":"Method","id":{"krate":0,"index":115},"span":{"file_name":"/Users/doviethoang/.cargo/registry/src/github.com-1ecc6299db9ec823/clru-0.2.1/src/lib.rs","byte_start":12863,"byte_end":12866,"line_start":434,"line_end":434,"column_start":12,"column_end":15},"name":"len","qualname":"<CLruCache<K, V, S>>::len","value":"pub fn len(&Self) -> usize","parent":null,"children":[],"decl_id":null,"docs":" Returns the number of key-value pairs that are currently in the the cache.\n","sig":null,"attributes":[{"value":"/ Returns the number of key-value pairs that are currently in the the cache.","span":{"file_name":"/Users/doviethoang/.cargo/registry/src/github.com-1ecc6299db9ec823/clru-0.2.1/src/lib.rs","byte_start":12773,"byte_end":12851,"line_start":433,"line_end":433,"column_start":5,"column_end":83}}]},{"kind":"Method","id":{"krate":0,"index":116},"span":{"file_name":"/Users/doviethoang/.cargo/registry/src/github.com-1ecc6299db9ec823/clru-0.2.1/src/lib.rs","byte_start":13069,"byte_end":13077,"line_start":440,"line_end":440,"column_start":12,"column_end":20},"name":"capacity","qualname":"<CLruCache<K, V, S>>::capacity","value":"pub fn capacity(&Self) -> usize","parent":null,"children":[],"decl_id":null,"docs":" Returns the maximum number of key-value pairs the cache can hold.\n","sig":null,"attributes":[{"value":"/ Returns the maximum number of key-value pairs the cache can hold.","span":{"file_name":"/Users/doviethoang/.cargo/registry/src/github.com-1ecc6299db9ec823/clru-0.2.1/src/lib.rs","byte_start":12988,"byte_end":13057,"line_start":439,"line_end":439,"column_start":5,"column_end":74}}]},{"kind":"Method","id":{"krate":0,"index":117},"span":{"file_name":"/Users/doviethoang/.cargo/registry/src/github.com-1ecc6299db9ec823/clru-0.2.1/src/lib.rs","byte_start":13215,"byte_end":13223,"line_start":445,"line_end":445,"column_start":12,"column_end":20},"name":"is_empty","qualname":"<CLruCache<K, V, S>>::is_empty","value":"pub fn is_empty(&Self) -> bool","parent":null,"children":[],"decl_id":null,"docs":" Returns a bool indicating whether the cache is empty or not.\n","sig":null,"attributes":[{"value":"/ Returns a bool indicating whether the cache is empty or not.","span":{"file_name":"/Users/doviethoang/.cargo/registry/src/github.com-1ecc6299db9ec823/clru-0.2.1/src/lib.rs","byte_start":13139,"byte_end":13203,"line_start":444,"line_end":444,"column_start":5,"column_end":69}}]},{"kind":"Method","id":{"krate":0,"index":118},"span":{"file_name":"/Users/doviethoang/.cargo/registry/src/github.com-1ecc6299db9ec823/clru-0.2.1/src/lib.rs","byte_start":13434,"byte_end":13441,"line_start":451,"line_end":451,"column_start":12,"column_end":19},"name":"is_full","qualname":"<CLruCache<K, V, S>>::is_full","value":"pub fn is_full(&Self) -> bool","parent":null,"children":[],"decl_id":null,"docs":" Returns a bool indicating whether the cache is full or not.\n","sig":null,"attributes":[{"value":"/ Returns a bool indicating whether the cache is full or not.","span":{"file_name":"/Users/doviethoang/.cargo/registry/src/github.com-1ecc6299db9ec823/clru-0.2.1/src/lib.rs","byte_start":13359,"byte_end":13422,"line_start":450,"line_end":450,"column_start":5,"column_end":68}}]},{"kind":"Method","id":{"krate":0,"index":119},"span":{"file_name":"/Users/doviethoang/.cargo/registry/src/github.com-1ecc6299db9ec823/clru-0.2.1/src/lib.rs","byte_start":13841,"byte_end":13846,"line_start":461,"line_end":461,"column_start":12,"column_end":17},"name":"front","qualname":"<CLruCache<K, V, S>>::front","value":"pub fn front(&Self) -> Option<(&K, &V)>","parent":null,"children":[],"decl_id":null,"docs":" Returns the value corresponding to the most recently used item or `None` if the cache is empty.\n Like `peek`, `font` does not update the LRU list so the item's position will be unchanged.\n","sig":null,"attributes":[{"value":"/ Returns the value corresponding to the most recently used item or `None` if the cache is empty.","span":{"file_name":"/Users/doviethoang/.cargo/registry/src/github.com-1ecc6299db9ec823/clru-0.2.1/src/lib.rs","byte_start":13631,"byte_end":13730,"line_start":459,"line_end":459,"column_start":5,"column_end":104}},{"value":"/ Like `peek`, `font` does not update the LRU list so the item's position will be unchanged.","span":{"file_name":"/Users/doviethoang/.cargo/registry/src/github.com-1ecc6299db9ec823/clru-0.2.1/src/lib.rs","byte_start":13735,"byte_end":13829,"line_start":460,"line_end":460,"column_start":5,"column_end":99}}]},{"kind":"Method","id":{"krate":0,"index":121},"span":{"file_name":"/Users/doviethoang/.cargo/registry/src/github.com-1ecc6299db9ec823/clru-0.2.1/src/lib.rs","byte_start":14161,"byte_end":14170,"line_start":467,"line_end":467,"column_start":12,"column_end":21},"name":"front_mut","qualname":"<CLruCache<K, V, S>>::front_mut","value":"pub fn front_mut(&mut Self) -> Option<(&K, &mut V)>","parent":null,"children":[],"decl_id":null,"docs":" Returns the value corresponding to the most recently used item or `None` if the cache is empty.\n Like `peek`, `font` does not update the LRU list so the item's position will be unchanged.\n","sig":null,"attributes":[{"value":"/ Returns the value corresponding to the most recently used item or `None` if the cache is empty.","span":{"file_name":"/Users/doviethoang/.cargo/registry/src/github.com-1ecc6299db9ec823/clru-0.2.1/src/lib.rs","byte_start":13951,"byte_end":14050,"line_start":465,"line_end":465,"column_start":5,"column_end":104}},{"value":"/ Like `peek`, `font` does not update the LRU list so the item's position will be unchanged.","span":{"file_name":"/Users/doviethoang/.cargo/registry/src/github.com-1ecc6299db9ec823/clru-0.2.1/src/lib.rs","byte_start":14055,"byte_end":14149,"line_start":466,"line_end":466,"column_start":5,"column_end":99}}]},{"kind":"Method","id":{"krate":0,"index":123},"span":{"file_name":"/Users/doviethoang/.cargo/registry/src/github.com-1ecc6299db9ec823/clru-0.2.1/src/lib.rs","byte_start":14498,"byte_end":14502,"line_start":473,"line_end":473,"column_start":12,"column_end":16},"name":"back","qualname":"<CLruCache<K, V, S>>::back","value":"pub fn back(&Self) -> Option<(&K, &V)>","parent":null,"children":[],"decl_id":null,"docs":" Returns the value corresponding to the least recently used item or `None` if the cache is empty.\n Like `peek`, `back` does not update the LRU list so the item's position will be unchanged.\n","sig":null,"attributes":[{"value":"/ Returns the value corresponding to the least recently used item or `None` if the cache is empty.","span":{"file_name":"/Users/doviethoang/.cargo/registry/src/github.com-1ecc6299db9ec823/clru-0.2.1/src/lib.rs","byte_start":14287,"byte_end":14387,"line_start":471,"line_end":471,"column_start":5,"column_end":105}},{"value":"/ Like `peek`, `back` does not update the LRU list so the item's position will be unchanged.","span":{"file_name":"/Users/doviethoang/.cargo/registry/src/github.com-1ecc6299db9ec823/clru-0.2.1/src/lib.rs","byte_start":14392,"byte_end":14486,"line_start":472,"line_end":472,"column_start":5,"column_end":99}}]},{"kind":"Method","id":{"krate":0,"index":125},"span":{"file_name":"/Users/doviethoang/.cargo/registry/src/github.com-1ecc6299db9ec823/clru-0.2.1/src/lib.rs","byte_start":14819,"byte_end":14827,"line_start":479,"line_end":479,"column_start":12,"column_end":20},"name":"back_mut","qualname":"<CLruCache<K, V, S>>::back_mut","value":"pub fn back_mut(&mut Self) -> Option<(&K, &mut V)>","parent":null,"children":[],"decl_id":null,"docs":" Returns the value corresponding to the least recently used item or `None` if the cache is empty.\n Like `peek`, `back` does not update the LRU list so the item's position will be unchanged.\n","sig":null,"attributes":[{"value":"/ Returns the value corresponding to the least recently used item or `None` if the cache is empty.","span":{"file_name":"/Users/doviethoang/.cargo/registry/src/github.com-1ecc6299db9ec823/clru-0.2.1/src/lib.rs","byte_start":14608,"byte_end":14708,"line_start":477,"line_end":477,"column_start":5,"column_end":105}},{"value":"/ Like `peek`, `back` does not update the LRU list so the item's position will be unchanged.","span":{"file_name":"/Users/doviethoang/.cargo/registry/src/github.com-1ecc6299db9ec823/clru-0.2.1/src/lib.rs","byte_start":14713,"byte_end":14807,"line_start":478,"line_end":478,"column_start":5,"column_end":99}}]},{"kind":"Method","id":{"krate":0,"index":127},"span":{"file_name":"/Users/doviethoang/.cargo/registry/src/github.com-1ecc6299db9ec823/clru-0.2.1/src/lib.rs","byte_start":15140,"byte_end":15143,"line_start":486,"line_end":486,"column_start":12,"column_end":15},"name":"put","qualname":"<CLruCache<K, V, S>>::put","value":"pub fn put(&mut Self, K, V) -> Option<V>","parent":null,"children":[],"decl_id":null,"docs":" Puts a key-value pair into cache.\n If the key already exists in the cache, then it updates the key's value and returns the old value.\n Otherwise, `None` is returned.\n","sig":null,"attributes":[{"value":"/ Puts a key-value pair into cache.","span":{"file_name":"/Users/doviethoang/.cargo/registry/src/github.com-1ecc6299db9ec823/clru-0.2.1/src/lib.rs","byte_start":14945,"byte_end":14982,"line_start":483,"line_end":483,"column_start":5,"column_end":42}},{"value":"/ If the key already exists in the cache, then it updates the key's value and returns the old value.","span":{"file_name":"/Users/doviethoang/.cargo/registry/src/github.com-1ecc6299db9ec823/clru-0.2.1/src/lib.rs","byte_start":14987,"byte_end":15089,"line_start":484,"line_end":484,"column_start":5,"column_end":107}},{"value":"/ Otherwise, `None` is returned.","span":{"file_name":"/Users/doviethoang/.cargo/registry/src/github.com-1ecc6299db9ec823/clru-0.2.1/src/lib.rs","byte_start":15094,"byte_end":15128,"line_start":485,"line_end":485,"column_start":5,"column_end":39}}]},{"kind":"Method","id":{"krate":0,"index":130},"span":{"file_name":"/Users/doviethoang/.cargo/registry/src/github.com-1ecc6299db9ec823/clru-0.2.1/src/lib.rs","byte_start":16342,"byte_end":16345,"line_start":515,"line_end":515,"column_start":12,"column_end":15},"name":"get","qualname":"<CLruCache<K, V, S>>::get","value":"pub fn get<Q: ?Sized>(&mut Self, &Q) -> Option<&V> where K: Borrow<Q>,\nQ: Hash + Eq","parent":null,"children":[],"decl_id":null,"docs":" Returns a reference to the value of the key in the cache or `None` if it is not present in the cache.\n Moves the key to the head of the LRU list if it exists.\n","sig":null,"attributes":[{"value":"/ Returns a reference to the value of the key in the cache or `None` if it is not present in the cache.","span":{"file_name":"/Users/doviethoang/.cargo/registry/src/github.com-1ecc6299db9ec823/clru-0.2.1/src/lib.rs","byte_start":16161,"byte_end":16266,"line_start":513,"line_end":513,"column_start":5,"column_end":110}},{"value":"/ Moves the key to the head of the LRU list if it exists.","span":{"file_name":"/Users/doviethoang/.cargo/registry/src/github.com-1ecc6299db9ec823/clru-0.2.1/src/lib.rs","byte_start":16271,"byte_end":16330,"line_start":514,"line_end":514,"column_start":5,"column_end":64}}]},{"kind":"Method","id":{"krate":0,"index":133},"span":{"file_name":"/Users/doviethoang/.cargo/registry/src/github.com-1ecc6299db9ec823/clru-0.2.1/src/lib.rs","byte_start":16850,"byte_end":16857,"line_start":528,"line_end":528,"column_start":12,"column_end":19},"name":"get_mut","qualname":"<CLruCache<K, V, S>>::get_mut","value":"pub fn get_mut<Q: ?Sized>(&mut Self, &Q) -> Option<&mut V> where K: Borrow<Q>,\nQ: Hash + Eq","parent":null,"children":[],"decl_id":null,"docs":" Returns a mutable reference to the value of the key in the cache or `None` if it is not present in the cache.\n Moves the key to the head of the LRU list if it exists.\n","sig":null,"attributes":[{"value":"/ Returns a mutable reference to the value of the key in the cache or `None` if it is not present in the cache.","span":{"file_name":"/Users/doviethoang/.cargo/registry/src/github.com-1ecc6299db9ec823/clru-0.2.1/src/lib.rs","byte_start":16661,"byte_end":16774,"line_start":526,"line_end":526,"column_start":5,"column_end":118}},{"value":"/ Moves the key to the head of the LRU list if it exists.","span":{"file_name":"/Users/doviethoang/.cargo/registry/src/github.com-1ecc6299db9ec823/clru-0.2.1/src/lib.rs","byte_start":16779,"byte_end":16838,"line_start":527,"line_end":527,"column_start":5,"column_end":64}}]},{"kind":"Method","id":{"krate":0,"index":136},"span":{"file_name":"/Users/doviethoang/.cargo/registry/src/github.com-1ecc6299db9ec823/clru-0.2.1/src/lib.rs","byte_start":17292,"byte_end":17295,"line_start":540,"line_end":540,"column_start":12,"column_end":15},"name":"pop","qualname":"<CLruCache<K, V, S>>::pop","value":"pub fn pop<Q: ?Sized>(&mut Self, &Q) -> Option<V> where K: Borrow<Q>,\nQ: Hash + Eq","parent":null,"children":[],"decl_id":null,"docs":" Removes and returns the value corresponding to the key from the cache or `None` if it does not exist.\n","sig":null,"attributes":[{"value":"/ Removes and returns the value corresponding to the key from the cache or `None` if it does not exist.","span":{"file_name":"/Users/doviethoang/.cargo/registry/src/github.com-1ecc6299db9ec823/clru-0.2.1/src/lib.rs","byte_start":17175,"byte_end":17280,"line_start":539,"line_end":539,"column_start":5,"column_end":110}}]},{"kind":"Method","id":{"krate":0,"index":139},"span":{"file_name":"/Users/doviethoang/.cargo/registry/src/github.com-1ecc6299db9ec823/clru-0.2.1/src/lib.rs","byte_start":17685,"byte_end":17694,"line_start":551,"line_end":551,"column_start":12,"column_end":21},"name":"pop_front","qualname":"<CLruCache<K, V, S>>::pop_front","value":"pub fn pop_front(&mut Self) -> Option<(K, V)>","parent":null,"children":[],"decl_id":null,"docs":" Removes and returns the key and value corresponding to the most recently used item or `None` if the cache is empty.\n","sig":null,"attributes":[{"value":"/ Removes and returns the key and value corresponding to the most recently used item or `None` if the cache is empty.","span":{"file_name":"/Users/doviethoang/.cargo/registry/src/github.com-1ecc6299db9ec823/clru-0.2.1/src/lib.rs","byte_start":17554,"byte_end":17673,"line_start":550,"line_end":550,"column_start":5,"column_end":124}}]},{"kind":"Method","id":{"krate":0,"index":140},"span":{"file_name":"/Users/doviethoang/.cargo/registry/src/github.com-1ecc6299db9ec823/clru-0.2.1/src/lib.rs","byte_start":18193,"byte_end":18201,"line_start":565,"line_end":565,"column_start":12,"column_end":20},"name":"pop_back","qualname":"<CLruCache<K, V, S>>::pop_back","value":"pub fn pop_back(&mut Self) -> Option<(K, V)>","parent":null,"children":[],"decl_id":null,"docs":" Removes and returns the key and value corresponding to the least recently used item or `None` if the cache is empty.\n","sig":null,"attributes":[{"value":"/ Removes and returns the key and value corresponding to the least recently used item or `None` if the cache is empty.","span":{"file_name":"/Users/doviethoang/.cargo/registry/src/github.com-1ecc6299db9ec823/clru-0.2.1/src/lib.rs","byte_start":18061,"byte_end":18181,"line_start":564,"line_end":564,"column_start":5,"column_end":125}}]},{"kind":"Method","id":{"krate":0,"index":141},"span":{"file_name":"/Users/doviethoang/.cargo/registry/src/github.com-1ecc6299db9ec823/clru-0.2.1/src/lib.rs","byte_start":18797,"byte_end":18801,"line_start":580,"line_end":580,"column_start":12,"column_end":16},"name":"peek","qualname":"<CLruCache<K, V, S>>::peek","value":"pub fn peek<Q: ?Sized>(&Self, &Q) -> Option<&V> where K: Borrow<Q>, Q: Hash +\nEq","parent":null,"children":[],"decl_id":null,"docs":" Returns a reference to the value corresponding to the key in the cache or `None` if it is not present in the cache.\n Unlike `get`, `peek` does not update the LRU list so the key's position will be unchanged.\n","sig":null,"attributes":[{"value":"/ Returns a reference to the value corresponding to the key in the cache or `None` if it is not present in the cache.","span":{"file_name":"/Users/doviethoang/.cargo/registry/src/github.com-1ecc6299db9ec823/clru-0.2.1/src/lib.rs","byte_start":18567,"byte_end":18686,"line_start":578,"line_end":578,"column_start":5,"column_end":124}},{"value":"/ Unlike `get`, `peek` does not update the LRU list so the key's position will be unchanged.","span":{"file_name":"/Users/doviethoang/.cargo/registry/src/github.com-1ecc6299db9ec823/clru-0.2.1/src/lib.rs","byte_start":18691,"byte_end":18785,"line_start":579,"line_end":579,"column_start":5,"column_end":99}}]},{"kind":"Method","id":{"krate":0,"index":144},"span":{"file_name":"/Users/doviethoang/.cargo/registry/src/github.com-1ecc6299db9ec823/clru-0.2.1/src/lib.rs","byte_start":19304,"byte_end":19312,"line_start":592,"line_end":592,"column_start":12,"column_end":20},"name":"peek_mut","qualname":"<CLruCache<K, V, S>>::peek_mut","value":"pub fn peek_mut<Q: ?Sized>(&mut Self, &Q) -> Option<&mut V> where\nK: Borrow<Q>, Q: Hash + Eq","parent":null,"children":[],"decl_id":null,"docs":" Returns a mutable reference to the value corresponding to the key in the cache or `None` if it is not present in the cache.\n Unlike `get_mut`, `peek_mut` does not update the LRU list so the key's position will be unchanged.\n","sig":null,"attributes":[{"value":"/ Returns a mutable reference to the value corresponding to the key in the cache or `None` if it is not present in the cache.","span":{"file_name":"/Users/doviethoang/.cargo/registry/src/github.com-1ecc6299db9ec823/clru-0.2.1/src/lib.rs","byte_start":19058,"byte_end":19185,"line_start":590,"line_end":590,"column_start":5,"column_end":132}},{"value":"/ Unlike `get_mut`, `peek_mut` does not update the LRU list so the key's position will be unchanged.","span":{"file_name":"/Users/doviethoang/.cargo/registry/src/github.com-1ecc6299db9ec823/clru-0.2.1/src/lib.rs","byte_start":19190,"byte_end":19292,"line_start":591,"line_end":591,"column_start":5,"column_end":107}}]},{"kind":"Method","id":{"krate":0,"index":147},"span":{"file_name":"/Users/doviethoang/.cargo/registry/src/github.com-1ecc6299db9ec823/clru-0.2.1/src/lib.rs","byte_start":19699,"byte_end":19707,"line_start":604,"line_end":604,"column_start":12,"column_end":20},"name":"contains","qualname":"<CLruCache<K, V, S>>::contains","value":"pub fn contains<Q: ?Sized>(&mut Self, &Q) -> bool where K: Borrow<Q>,\nQ: Hash + Eq","parent":null,"children":[],"decl_id":null,"docs":" Returns a bool indicating whether the given key is in the cache.\n Does not update the LRU list.\n","sig":null,"attributes":[{"value":"/ Returns a bool indicating whether the given key is in the cache.","span":{"file_name":"/Users/doviethoang/.cargo/registry/src/github.com-1ecc6299db9ec823/clru-0.2.1/src/lib.rs","byte_start":19581,"byte_end":19649,"line_start":602,"line_end":602,"column_start":5,"column_end":73}},{"value":"/ Does not update the LRU list.","span":{"file_name":"/Users/doviethoang/.cargo/registry/src/github.com-1ecc6299db9ec823/clru-0.2.1/src/lib.rs","byte_start":19654,"byte_end":19687,"line_start":603,"line_end":603,"column_start":5,"column_end":38}}]},{"kind":"Method","id":{"krate":0,"index":149},"span":{"file_name":"/Users/doviethoang/.cargo/registry/src/github.com-1ecc6299db9ec823/clru-0.2.1/src/lib.rs","byte_start":19900,"byte_end":19905,"line_start":613,"line_end":613,"column_start":12,"column_end":17},"name":"clear","qualname":"<CLruCache<K, V, S>>::clear","value":"pub fn clear(&mut Self)","parent":null,"children":[],"decl_id":null,"docs":" Clears the contents of the cache.\n","sig":null,"attributes":[{"value":"/ Clears the contents of the cache.","span":{"file_name":"/Users/doviethoang/.cargo/registry/src/github.com-1ecc6299db9ec823/clru-0.2.1/src/lib.rs","byte_start":19851,"byte_end":19888,"line_start":612,"line_end":612,"column_start":5,"column_end":42}}]},{"kind":"Method","id":{"krate":0,"index":150},"span":{"file_name":"/Users/doviethoang/.cargo/registry/src/github.com-1ecc6299db9ec823/clru-0.2.1/src/lib.rs","byte_start":20110,"byte_end":20114,"line_start":620,"line_end":620,"column_start":12,"column_end":16},"name":"iter","qualname":"<CLruCache<K, V, S>>::iter","value":"pub fn iter(&Self) -> CLruCacheIter<, K, V>","parent":null,"children":[],"decl_id":null,"docs":" Returns an iterator visiting all entries in order.\n The iterator element type is `(&'a K, &'a V)`.\n","sig":null,"attributes":[{"value":"/ Returns an iterator visiting all entries in order.","span":{"file_name":"/Users/doviethoang/.cargo/registry/src/github.com-1ecc6299db9ec823/clru-0.2.1/src/lib.rs","byte_start":19989,"byte_end":20043,"line_start":618,"line_end":618,"column_start":5,"column_end":59}},{"value":"/ The iterator element type is `(&'a K, &'a V)`.","span":{"file_name":"/Users/doviethoang/.cargo/registry/src/github.com-1ecc6299db9ec823/clru-0.2.1/src/lib.rs","byte_start":20048,"byte_end":20098,"line_start":619,"line_end":619,"column_start":5,"column_end":55}}]},{"kind":"Method","id":{"krate":0,"index":151},"span":{"file_name":"/Users/doviethoang/.cargo/registry/src/github.com-1ecc6299db9ec823/clru-0.2.1/src/lib.rs","byte_start":20393,"byte_end":20401,"line_start":628,"line_end":628,"column_start":12,"column_end":20},"name":"iter_mut","qualname":"<CLruCache<K, V, S>>::iter_mut","value":"pub fn iter_mut(&mut Self) -> CLruCacheIterMut<, K, V>","parent":null,"children":[],"decl_id":null,"docs":" Returns an iterator visiting all entries in order, giving a mutable reference on V.\n The iterator element type is `(&'a K, &'a mut V)`.\n","sig":null,"attributes":[{"value":"/ Returns an iterator visiting all entries in order, giving a mutable reference on V.","span":{"file_name":"/Users/doviethoang/.cargo/registry/src/github.com-1ecc6299db9ec823/clru-0.2.1/src/lib.rs","byte_start":20235,"byte_end":20322,"line_start":626,"line_end":626,"column_start":5,"column_end":92}},{"value":"/ The iterator element type is `(&'a K, &'a mut V)`.","span":{"file_name":"/Users/doviethoang/.cargo/registry/src/github.com-1ecc6299db9ec823/clru-0.2.1/src/lib.rs","byte_start":20327,"byte_end":20381,"line_start":627,"line_end":627,"column_start":5,"column_end":59}}]},{"kind":"Method","id":{"krate":0,"index":152},"span":{"file_name":"/Users/doviethoang/.cargo/registry/src/github.com-1ecc6299db9ec823/clru-0.2.1/src/lib.rs","byte_start":20693,"byte_end":20699,"line_start":636,"line_end":636,"column_start":12,"column_end":18},"name":"resize","qualname":"<CLruCache<K, V, S>>::resize","value":"pub fn resize(&mut Self, usize)","parent":null,"children":[],"decl_id":null,"docs":" Resizes the cache.\n If the new capacity is smaller than the size of the current cache any entries past the new capacity are discarded.\n","sig":null,"attributes":[{"value":"/ Resizes the cache.","span":{"file_name":"/Users/doviethoang/.cargo/registry/src/github.com-1ecc6299db9ec823/clru-0.2.1/src/lib.rs","byte_start":20536,"byte_end":20558,"line_start":634,"line_end":634,"column_start":5,"column_end":27}},{"value":"/ If the new capacity is smaller than the size of the current cache any entries past the new capacity are discarded.","span":{"file_name":"/Users/doviethoang/.cargo/registry/src/github.com-1ecc6299db9ec823/clru-0.2.1/src/lib.rs","byte_start":20563,"byte_end":20681,"line_start":635,"line_end":635,"column_start":5,"column_end":123}}]},{"kind":"Struct","id":{"krate":0,"index":278},"span":{"file_name":"/Users/doviethoang/.cargo/registry/src/github.com-1ecc6299db9ec823/clru-0.2.1/src/lib.rs","byte_start":21446,"byte_end":21459,"line_start":658,"line_end":658,"column_start":12,"column_end":25},"name":"CLruCacheIter","qualname":"::CLruCacheIter","value":"CLruCacheIter {  }","parent":null,"children":[{"krate":0,"index":282}],"decl_id":null,"docs":" An iterator over the entries of a `CLruCache`.","sig":null,"attributes":[{"value":"/ An iterator over the entries of a `CLruCache`.","span":{"file_name":"/Users/doviethoang/.cargo/registry/src/github.com-1ecc6299db9ec823/clru-0.2.1/src/lib.rs","byte_start":21144,"byte_end":21194,"line_start":650,"line_end":650,"column_start":1,"column_end":51}},{"value":"/","span":{"file_name":"/Users/doviethoang/.cargo/registry/src/github.com-1ecc6299db9ec823/clru-0.2.1/src/lib.rs","byte_start":21195,"byte_end":21198,"line_start":651,"line_end":651,"column_start":1,"column_end":4}},{"value":"/ This `struct` is created by the [`iter`] method on [`CLruCache`][`CLruCache`].","span":{"file_name":"/Users/doviethoang/.cargo/registry/src/github.com-1ecc6299db9ec823/clru-0.2.1/src/lib.rs","byte_start":21199,"byte_end":21281,"line_start":652,"line_end":652,"column_start":1,"column_end":83}},{"value":"/ See its documentation for more.","span":{"file_name":"/Users/doviethoang/.cargo/registry/src/github.com-1ecc6299db9ec823/clru-0.2.1/src/lib.rs","byte_start":21282,"byte_end":21317,"line_start":653,"line_end":653,"column_start":1,"column_end":36}},{"value":"/","span":{"file_name":"/Users/doviethoang/.cargo/registry/src/github.com-1ecc6299db9ec823/clru-0.2.1/src/lib.rs","byte_start":21318,"byte_end":21321,"line_start":654,"line_end":654,"column_start":1,"column_end":4}},{"value":"/ [`iter`]: struct.CLruCache.html#method.iter","span":{"file_name":"/Users/doviethoang/.cargo/registry/src/github.com-1ecc6299db9ec823/clru-0.2.1/src/lib.rs","byte_start":21322,"byte_end":21369,"line_start":655,"line_end":655,"column_start":1,"column_end":48}},{"value":"/ [`CLruCache`]: struct.CLruCache.html","span":{"file_name":"/Users/doviethoang/.cargo/registry/src/github.com-1ecc6299db9ec823/clru-0.2.1/src/lib.rs","byte_start":21370,"byte_end":21410,"line_start":656,"line_end":656,"column_start":1,"column_end":41}}]},{"kind":"Struct","id":{"krate":0,"index":172},"span":{"file_name":"/Users/doviethoang/.cargo/registry/src/github.com-1ecc6299db9ec823/clru-0.2.1/src/lib.rs","byte_start":22428,"byte_end":22444,"line_start":693,"line_end":693,"column_start":12,"column_end":28},"name":"CLruCacheIterMut","qualname":"::CLruCacheIterMut","value":"CLruCacheIterMut {  }","parent":null,"children":[{"krate":0,"index":176}],"decl_id":null,"docs":" An iterator over mutables entries of a `CLruCache`.","sig":null,"attributes":[{"value":"/ An iterator over mutables entries of a `CLruCache`.","span":{"file_name":"/Users/doviethoang/.cargo/registry/src/github.com-1ecc6299db9ec823/clru-0.2.1/src/lib.rs","byte_start":22133,"byte_end":22188,"line_start":686,"line_end":686,"column_start":1,"column_end":56}},{"value":"/","span":{"file_name":"/Users/doviethoang/.cargo/registry/src/github.com-1ecc6299db9ec823/clru-0.2.1/src/lib.rs","byte_start":22189,"byte_end":22192,"line_start":687,"line_end":687,"column_start":1,"column_end":4}},{"value":"/ This `struct` is created by the [`iter_mut`] method on [`CLruCache`][`CLruCache`].","span":{"file_name":"/Users/doviethoang/.cargo/registry/src/github.com-1ecc6299db9ec823/clru-0.2.1/src/lib.rs","byte_start":22193,"byte_end":22279,"line_start":688,"line_end":688,"column_start":1,"column_end":87}},{"value":"/ See its documentation for more.","span":{"file_name":"/Users/doviethoang/.cargo/registry/src/github.com-1ecc6299db9ec823/clru-0.2.1/src/lib.rs","byte_start":22280,"byte_end":22315,"line_start":689,"line_end":689,"column_start":1,"column_end":36}},{"value":"/","span":{"file_name":"/Users/doviethoang/.cargo/registry/src/github.com-1ecc6299db9ec823/clru-0.2.1/src/lib.rs","byte_start":22316,"byte_end":22319,"line_start":690,"line_end":690,"column_start":1,"column_end":4}},{"value":"/ [`iter_mut`]: struct.CLruCache.html#method.iter_mut","span":{"file_name":"/Users/doviethoang/.cargo/registry/src/github.com-1ecc6299db9ec823/clru-0.2.1/src/lib.rs","byte_start":22320,"byte_end":22375,"line_start":691,"line_end":691,"column_start":1,"column_end":56}},{"value":"/ [`CLruCache`]: struct.CLruCache.html","span":{"file_name":"/Users/doviethoang/.cargo/registry/src/github.com-1ecc6299db9ec823/clru-0.2.1/src/lib.rs","byte_start":22376,"byte_end":22416,"line_start":692,"line_end":692,"column_start":1,"column_end":41}}]}],"impls":[{"id":0,"kind":"Inherent","span":{"file_name":"/Users/doviethoang/.cargo/registry/src/github.com-1ecc6299db9ec823/clru-0.2.1/src/lib.rs","byte_start":1845,"byte_end":1858,"line_start":69,"line_end":69,"column_start":9,"column_end":22},"value":"","parent":null,"children":[{"krate":0,"index":30},{"krate":0,"index":31},{"krate":0,"index":32},{"krate":0,"index":33},{"krate":0,"index":34},{"krate":0,"index":35},{"krate":0,"index":37},{"krate":0,"index":39},{"krate":0,"index":41},{"krate":0,"index":43},{"krate":0,"index":45},{"krate":0,"index":47},{"krate":0,"index":49},{"krate":0,"index":50},{"krate":0,"index":51},{"krate":0,"index":52},{"krate":0,"index":53},{"krate":0,"index":54},{"krate":0,"index":55},{"krate":0,"index":56}],"docs":"","sig":null,"attributes":[]},{"id":1,"kind":"Direct","span":{"file_name":"/Users/doviethoang/.cargo/registry/src/github.com-1ecc6299db9ec823/clru-0.2.1/src/lib.rs","byte_start":8316,"byte_end":8333,"line_start":288,"line_end":288,"column_start":26,"column_end":43},"value":"","parent":null,"children":[{"krate":0,"index":61},{"krate":0,"index":62},{"krate":0,"index":63}],"docs":"","sig":null,"attributes":[]},{"id":2,"kind":"Direct","span":{"file_name":"/Users/doviethoang/.cargo/registry/src/github.com-1ecc6299db9ec823/clru-0.2.1/src/lib.rs","byte_start":8828,"byte_end":8845,"line_start":308,"line_end":308,"column_start":37,"column_end":54},"value":"","parent":null,"children":[{"krate":0,"index":67}],"docs":"","sig":null,"attributes":[]},{"id":3,"kind":"Direct","span":{"file_name":"/Users/doviethoang/.cargo/registry/src/github.com-1ecc6299db9ec823/clru-0.2.1/src/lib.rs","byte_start":9211,"byte_end":9228,"line_start":322,"line_end":322,"column_start":35,"column_end":52},"value":"","parent":null,"children":[{"krate":0,"index":71}],"docs":"","sig":null,"attributes":[]},{"id":4,"kind":"Direct","span":{"file_name":"/Users/doviethoang/.cargo/registry/src/github.com-1ecc6299db9ec823/clru-0.2.1/src/lib.rs","byte_start":9455,"byte_end":9475,"line_start":335,"line_end":335,"column_start":26,"column_end":46},"value":"","parent":null,"children":[{"krate":0,"index":82},{"krate":0,"index":83},{"krate":0,"index":84}],"docs":"","sig":null,"attributes":[]},{"id":5,"kind":"Direct","span":{"file_name":"/Users/doviethoang/.cargo/registry/src/github.com-1ecc6299db9ec823/clru-0.2.1/src/lib.rs","byte_start":10645,"byte_end":10665,"line_start":363,"line_end":363,"column_start":37,"column_end":57},"value":"","parent":null,"children":[{"krate":0,"index":88}],"docs":"","sig":null,"attributes":[]},{"id":6,"kind":"Direct","span":{"file_name":"/Users/doviethoang/.cargo/registry/src/github.com-1ecc6299db9ec823/clru-0.2.1/src/lib.rs","byte_start":11203,"byte_end":11223,"line_start":380,"line_end":380,"column_start":35,"column_end":55},"value":"","parent":null,"children":[{"krate":0,"index":92}],"docs":"","sig":null,"attributes":[]},{"id":7,"kind":"Direct","span":{"file_name":"/Users/doviethoang/.cargo/registry/src/github.com-1ecc6299db9ec823/clru-0.2.1/src/lib.rs","byte_start":11807,"byte_end":11810,"line_start":402,"line_end":402,"column_start":53,"column_end":56},"value":"","parent":null,"children":[{"krate":0,"index":99}],"docs":"","sig":null,"attributes":[]},{"id":8,"kind":"Inherent","span":{"file_name":"/Users/doviethoang/.cargo/registry/src/github.com-1ecc6299db9ec823/clru-0.2.1/src/lib.rs","byte_start":12096,"byte_end":12105,"line_start":414,"line_end":414,"column_start":23,"column_end":32},"value":"","parent":null,"children":[{"krate":0,"index":109}],"docs":"","sig":null,"attributes":[]},{"id":9,"kind":"Inherent","span":{"file_name":"/Users/doviethoang/.cargo/registry/src/github.com-1ecc6299db9ec823/clru-0.2.1/src/lib.rs","byte_start":12402,"byte_end":12411,"line_start":424,"line_end":424,"column_start":39,"column_end":48},"value":"","parent":null,"children":[{"krate":0,"index":114},{"krate":0,"index":115},{"krate":0,"index":116},{"krate":0,"index":117},{"krate":0,"index":118},{"krate":0,"index":119},{"krate":0,"index":121},{"krate":0,"index":123},{"krate":0,"index":125},{"krate":0,"index":127},{"krate":0,"index":130},{"krate":0,"index":133},{"krate":0,"index":136},{"krate":0,"index":139},{"krate":0,"index":140},{"krate":0,"index":141},{"krate":0,"index":144},{"krate":0,"index":147},{"krate":0,"index":149},{"krate":0,"index":150},{"krate":0,"index":151},{"krate":0,"index":152}],"docs":"","sig":null,"attributes":[]},{"id":10,"kind":"Direct","span":{"file_name":"/Users/doviethoang/.cargo/registry/src/github.com-1ecc6299db9ec823/clru-0.2.1/src/lib.rs","byte_start":21549,"byte_end":21562,"line_start":662,"line_end":662,"column_start":29,"column_end":42},"value":"","parent":null,"children":[{"krate":0,"index":157},{"krate":0,"index":158},{"krate":0,"index":160}],"docs":"","sig":null,"attributes":[]},{"id":11,"kind":"Direct","span":{"file_name":"/Users/doviethoang/.cargo/registry/src/github.com-1ecc6299db9ec823/clru-0.2.1/src/lib.rs","byte_start":21854,"byte_end":21867,"line_start":674,"line_end":674,"column_start":40,"column_end":53},"value":"","parent":null,"children":[{"krate":0,"index":165}],"docs":"","sig":null,"attributes":[]},{"id":12,"kind":"Direct","span":{"file_name":"/Users/doviethoang/.cargo/registry/src/github.com-1ecc6299db9ec823/clru-0.2.1/src/lib.rs","byte_start":22045,"byte_end":22058,"line_start":680,"line_end":680,"column_start":38,"column_end":51},"value":"","parent":null,"children":[{"krate":0,"index":171}],"docs":"","sig":null,"attributes":[]},{"id":13,"kind":"Direct","span":{"file_name":"/Users/doviethoang/.cargo/registry/src/github.com-1ecc6299db9ec823/clru-0.2.1/src/lib.rs","byte_start":22537,"byte_end":22553,"line_start":697,"line_end":697,"column_start":29,"column_end":45},"value":"","parent":null,"children":[{"krate":0,"index":181},{"krate":0,"index":182},{"krate":0,"index":184}],"docs":"","sig":null,"attributes":[]},{"id":14,"kind":"Direct","span":{"file_name":"/Users/doviethoang/.cargo/registry/src/github.com-1ecc6299db9ec823/clru-0.2.1/src/lib.rs","byte_start":22852,"byte_end":22868,"line_start":709,"line_end":709,"column_start":40,"column_end":56},"value":"","parent":null,"children":[{"krate":0,"index":189}],"docs":"","sig":null,"attributes":[]},{"id":15,"kind":"Direct","span":{"file_name":"/Users/doviethoang/.cargo/registry/src/github.com-1ecc6299db9ec823/clru-0.2.1/src/lib.rs","byte_start":23075,"byte_end":23091,"line_start":717,"line_end":717,"column_start":38,"column_end":54},"value":"","parent":null,"children":[{"krate":0,"index":195}],"docs":"","sig":null,"attributes":[]}],"refs":[],"macro_refs":[],"relations":[{"span":{"file_name":"/Users/doviethoang/.cargo/registry/src/github.com-1ecc6299db9ec823/clru-0.2.1/src/lib.rs","byte_start":1845,"byte_end":1858,"line_start":69,"line_end":69,"column_start":9,"column_end":22},"kind":{"Impl":{"id":0}},"from":{"krate":0,"index":204},"to":{"krate":4294967295,"index":4294967295}},{"span":{"file_name":"/Users/doviethoang/.cargo/registry/src/github.com-1ecc6299db9ec823/clru-0.2.1/src/lib.rs","byte_start":8316,"byte_end":8333,"line_start":288,"line_end":288,"column_start":26,"column_end":43},"kind":{"Impl":{"id":1}},"from":{"krate":0,"index":213},"to":{"krate":2,"index":7907}},{"span":{"file_name":"/Users/doviethoang/.cargo/registry/src/github.com-1ecc6299db9ec823/clru-0.2.1/src/lib.rs","byte_start":8828,"byte_end":8845,"line_start":308,"line_end":308,"column_start":37,"column_end":54},"kind":{"Impl":{"id":2}},"from":{"krate":0,"index":213},"to":{"krate":2,"index":7759}},{"span":{"file_name":"/Users/doviethoang/.cargo/registry/src/github.com-1ecc6299db9ec823/clru-0.2.1/src/lib.rs","byte_start":9211,"byte_end":9228,"line_start":322,"line_end":322,"column_start":35,"column_end":52},"kind":{"Impl":{"id":3}},"from":{"krate":0,"index":213},"to":{"krate":2,"index":7784}},{"span":{"file_name":"/Users/doviethoang/.cargo/registry/src/github.com-1ecc6299db9ec823/clru-0.2.1/src/lib.rs","byte_start":9455,"byte_end":9475,"line_start":335,"line_end":335,"column_start":26,"column_end":46},"kind":{"Impl":{"id":4}},"from":{"krate":0,"index":72},"to":{"krate":2,"index":7907}},{"span":{"file_name":"/Users/doviethoang/.cargo/registry/src/github.com-1ecc6299db9ec823/clru-0.2.1/src/lib.rs","byte_start":10645,"byte_end":10665,"line_start":363,"line_end":363,"column_start":37,"column_end":57},"kind":{"Impl":{"id":5}},"from":{"krate":0,"index":72},"to":{"krate":2,"index":7759}},{"span":{"file_name":"/Users/doviethoang/.cargo/registry/src/github.com-1ecc6299db9ec823/clru-0.2.1/src/lib.rs","byte_start":11203,"byte_end":11223,"line_start":380,"line_end":380,"column_start":35,"column_end":55},"kind":{"Impl":{"id":6}},"from":{"krate":0,"index":72},"to":{"krate":2,"index":7784}},{"span":{"file_name":"/Users/doviethoang/.cargo/registry/src/github.com-1ecc6299db9ec823/clru-0.2.1/src/lib.rs","byte_start":11807,"byte_end":11810,"line_start":402,"line_end":402,"column_start":53,"column_end":56},"kind":{"Impl":{"id":7}},"from":{"krate":0,"index":228},"to":{"krate":2,"index":2623}},{"span":{"file_name":"/Users/doviethoang/.cargo/registry/src/github.com-1ecc6299db9ec823/clru-0.2.1/src/lib.rs","byte_start":12096,"byte_end":12105,"line_start":414,"line_end":414,"column_start":23,"column_end":32},"kind":{"Impl":{"id":8}},"from":{"krate":0,"index":100},"to":{"krate":4294967295,"index":4294967295}},{"span":{"file_name":"/Users/doviethoang/.cargo/registry/src/github.com-1ecc6299db9ec823/clru-0.2.1/src/lib.rs","byte_start":12402,"byte_end":12411,"line_start":424,"line_end":424,"column_start":39,"column_end":48},"kind":{"Impl":{"id":9}},"from":{"krate":0,"index":100},"to":{"krate":4294967295,"index":4294967295}},{"span":{"file_name":"/Users/doviethoang/.cargo/registry/src/github.com-1ecc6299db9ec823/clru-0.2.1/src/lib.rs","byte_start":21549,"byte_end":21562,"line_start":662,"line_end":662,"column_start":29,"column_end":42},"kind":{"Impl":{"id":10}},"from":{"krate":0,"index":278},"to":{"krate":2,"index":7907}},{"span":{"file_name":"/Users/doviethoang/.cargo/registry/src/github.com-1ecc6299db9ec823/clru-0.2.1/src/lib.rs","byte_start":21854,"byte_end":21867,"line_start":674,"line_end":674,"column_start":40,"column_end":53},"kind":{"Impl":{"id":11}},"from":{"krate":0,"index":278},"to":{"krate":2,"index":7759}},{"span":{"file_name":"/Users/doviethoang/.cargo/registry/src/github.com-1ecc6299db9ec823/clru-0.2.1/src/lib.rs","byte_start":22045,"byte_end":22058,"line_start":680,"line_end":680,"column_start":38,"column_end":51},"kind":{"Impl":{"id":12}},"from":{"krate":0,"index":278},"to":{"krate":2,"index":7784}},{"span":{"file_name":"/Users/doviethoang/.cargo/registry/src/github.com-1ecc6299db9ec823/clru-0.2.1/src/lib.rs","byte_start":22537,"byte_end":22553,"line_start":697,"line_end":697,"column_start":29,"column_end":45},"kind":{"Impl":{"id":13}},"from":{"krate":0,"index":172},"to":{"krate":2,"index":7907}},{"span":{"file_name":"/Users/doviethoang/.cargo/registry/src/github.com-1ecc6299db9ec823/clru-0.2.1/src/lib.rs","byte_start":22852,"byte_end":22868,"line_start":709,"line_end":709,"column_start":40,"column_end":56},"kind":{"Impl":{"id":14}},"from":{"krate":0,"index":172},"to":{"krate":2,"index":7759}},{"span":{"file_name":"/Users/doviethoang/.cargo/registry/src/github.com-1ecc6299db9ec823/clru-0.2.1/src/lib.rs","byte_start":23075,"byte_end":23091,"line_start":717,"line_end":717,"column_start":38,"column_end":54},"kind":{"Impl":{"id":15}},"from":{"krate":0,"index":172},"to":{"krate":2,"index":7784}}]}